src/__init__.py
src/__main__.py
src/defaults/__init__.py
src/defaults/default_config.py
src/modules/__init__.py
src/modules/cli_execution.py
src/modules/configs.py
src/modules/csv_normalizer.py
src/modules/file_processing.py
csv_normalizer-0.1.4.dist-info/LICENSE
csv_normalizer-0.1.4.dist-info/METADATA
csv_normalizer-0.1.4.dist-info/WHEEL
csv_normalizer-0.1.4.dist-info/entry_points.txt
csv_normalizer-0.1.4.dist-info/top_level.txt
csv_normalizer-0.1.4.dist-info/RECORD
