Metadata-Version: 2.1
Name: csv-normalizer
Version: 0.1.4
Summary: csv normalize to have always same output csv
Home-page: https://github.com/CoffeeITWorks/csv_normalizer
Author: Pablo Estigarribia
Author-email: pablodav@gmail.com
License: MIT
Platform: UNKNOWN
Classifier: Development Status :: 5 - Production/Stable
Classifier: Intended Audience :: System Administrators
Classifier: Topic :: Utilities
Classifier: Intended Audience :: Telecommunications Industry
Classifier: Operating System :: OS Independent
Classifier: License :: OSI Approved :: MIT License
Classifier: Programming Language :: Python :: 3
Classifier: Programming Language :: Python :: 3 :: Only
License-File: LICENSE
Requires-Dist: pandas (>=0.24.2)
